ldclient/__init__.py
ldclient/client.py
ldclient/config.py
ldclient/context.py
ldclient/datasystem.py
ldclient/evaluation.py
ldclient/feature_store.py
ldclient/feature_store_helpers.py
ldclient/hook.py
ldclient/impl/__init__.py
ldclient/impl/big_segments.py
ldclient/impl/datasource/__init__.py
ldclient/impl/datasource/feature_requester.py
ldclient/impl/datasource/polling.py
ldclient/impl/datasource/status.py
ldclient/impl/datasource/streaming.py
ldclient/impl/datasourcev2/__init__.py
ldclient/impl/datasourcev2/polling.py
ldclient/impl/datasourcev2/streaming.py
ldclient/impl/datastore/__init__.py
ldclient/impl/datastore/status.py
ldclient/impl/datasystem/__init__.py
ldclient/impl/datasystem/fdv1.py
ldclient/impl/datasystem/fdv2.py
ldclient/impl/datasystem/protocolv2.py
ldclient/impl/datasystem/store.py
ldclient/impl/dependency_tracker.py
ldclient/impl/evaluator.py
ldclient/impl/events/__init__.py
ldclient/impl/events/diagnostics.py
ldclient/impl/events/event_context_formatter.py
ldclient/impl/events/event_processor.py
ldclient/impl/events/event_summarizer.py
ldclient/impl/events/types.py
ldclient/impl/fixed_thread_pool.py
ldclient/impl/flag_tracker.py
ldclient/impl/http.py
ldclient/impl/integrations/__init__.py
ldclient/impl/integrations/consul/__init__.py
ldclient/impl/integrations/consul/consul_feature_store.py
ldclient/impl/integrations/dynamodb/__init__.py
ldclient/impl/integrations/dynamodb/dynamodb_big_segment_store.py
ldclient/impl/integrations/dynamodb/dynamodb_feature_store.py
ldclient/impl/integrations/files/__init__.py
ldclient/impl/integrations/files/file_data_source.py
ldclient/impl/integrations/files/file_data_sourcev2.py
ldclient/impl/integrations/redis/__init__.py
ldclient/impl/integrations/redis/redis_big_segment_store.py
ldclient/impl/integrations/redis/redis_feature_store.py
ldclient/impl/integrations/test_data/__init__.py
ldclient/impl/integrations/test_data/test_data_source.py
ldclient/impl/integrations/test_datav2/__init__.py
launchdarkly_server_sdk-9.14.0.dist-info/METADATA
launchdarkly_server_sdk-9.14.0.dist-info/WHEEL
launchdarkly_server_sdk-9.14.0.dist-info/licenses/LICENSE.txt
launchdarkly_server_sdk-9.14.0.dist-info/RECORD
